odoo/addons/purchase_last_price_info/README.rst
odoo/addons/purchase_last_price_info/__init__.py
odoo/addons/purchase_last_price_info/__manifest__.py
odoo/addons/purchase_last_price_info/hooks.py
odoo/addons/purchase_last_price_info/i18n/ca.po
odoo/addons/purchase_last_price_info/i18n/de.po
odoo/addons/purchase_last_price_info/i18n/el_GR.po
odoo/addons/purchase_last_price_info/i18n/es.po
odoo/addons/purchase_last_price_info/i18n/es_ES.po
odoo/addons/purchase_last_price_info/i18n/eu.po
odoo/addons/purchase_last_price_info/i18n/fi.po
odoo/addons/purchase_last_price_info/i18n/fr.po
odoo/addons/purchase_last_price_info/i18n/fr_CH.po
odoo/addons/purchase_last_price_info/i18n/fr_FR.po
odoo/addons/purchase_last_price_info/i18n/gl.po
odoo/addons/purchase_last_price_info/i18n/hr.po
odoo/addons/purchase_last_price_info/i18n/hr_HR.po
odoo/addons/purchase_last_price_info/i18n/it.po
odoo/addons/purchase_last_price_info/i18n/nl.po
odoo/addons/purchase_last_price_info/i18n/nl_NL.po
odoo/addons/purchase_last_price_info/i18n/pt.po
odoo/addons/purchase_last_price_info/i18n/pt_BR.po
odoo/addons/purchase_last_price_info/i18n/purchase_last_price_info.pot
odoo/addons/purchase_last_price_info/i18n/ro.po
odoo/addons/purchase_last_price_info/i18n/ru.po
odoo/addons/purchase_last_price_info/i18n/sk.po
odoo/addons/purchase_last_price_info/i18n/sl.po
odoo/addons/purchase_last_price_info/i18n/tr.po
odoo/addons/purchase_last_price_info/i18n/tr_TR.po
odoo/addons/purchase_last_price_info/i18n/vi_VN.po
odoo/addons/purchase_last_price_info/i18n/zh_CN.po
odoo/addons/purchase_last_price_info/models/__init__.py
odoo/addons/purchase_last_price_info/models/product.py
odoo/addons/purchase_last_price_info/models/purchase.py
odoo/addons/purchase_last_price_info/readme/CONTRIBUTORS.rst
odoo/addons/purchase_last_price_info/readme/DESCRIPTION.rst
odoo/addons/purchase_last_price_info/readme/USAGE.rst
odoo/addons/purchase_last_price_info/static/description/icon.png
odoo12_addon_purchase_last_price_info-12.0.1.1.0.dist-info/METADATA
odoo12_addon_purchase_last_price_info-12.0.1.1.0.dist-info/WHEEL
odoo12_addon_purchase_last_price_info-12.0.1.1.0.dist-info/top_level.txt
odoo12_addon_purchase_last_price_info-12.0.1.1.0.dist-info/RECORD
