Metadata-Version: 2.1
Name: odoo12-addon-purchase-last-price-info
Version: 12.0.1.1.0
Summary: Purchase Product Last Price Info
Home-page: https://github.com/OCA/purchase-workflow
Author: OdooMRP team, AvanzOSC, Tecnativa - Pedro M. Baeza, Odoo Community Association (OCA)
Author-email: support@odoo-community.org
License: AGPL-3
Platform: UNKNOWN
Classifier: Programming Language :: Python
Classifier: Framework :: Odoo
Classifier: License :: OSI Approved :: GNU Affero General Public License v3
Classifier: Development Status :: 4 - Beta
Requires-Python: >=3.5
Requires-Dist: odoo (<12.1dev,>=12.0a)
